theotex/__init__.py
theotex/__main__.py
theotex/exceptions.py
theotex/logs.py
theotex/navigation.py
theotex/urls.py
theotex/util.py
theotex-1.0.0.dist-info/entry_points.txt
theotex-1.0.0.dist-info/LICENSE
theotex-1.0.0.dist-info/WHEEL
theotex-1.0.0.dist-info/METADATA
theotex-1.0.0.dist-info/RECORD
